setup.py
DelogX/DESCRIPTION.rst
DelogX/VERSION
DelogX/__init__.py
DelogX/__main__.py
DelogX.egg-info/PKG-INFO
DelogX.egg-info/SOURCES.txt
DelogX.egg-info/dependency_links.txt
DelogX.egg-info/entry_points.txt
DelogX.egg-info/requires.txt
DelogX.egg-info/top_level.txt
DelogX/defaults/config.json
DelogX/defaults/debug.py
DelogX/defaults/deploy/apache2.conf
DelogX/defaults/deploy/apache2_win.conf
DelogX/defaults/deploy/mod_wsgi.wsgi
DelogX/defaults/deploy/nginx.conf
DelogX/defaults/deploy/uwsgi.py
DelogX/defaults/plugins/__init__.py
DelogX/defaults/plugins/delog_ext_link/__init__.py
DelogX/defaults/plugins/delog_ext_link/plugin.json
DelogX/defaults/plugins/delog_feed/__init__.py
DelogX/defaults/plugins/delog_feed/config.json
DelogX/defaults/plugins/delog_feed/plugin.json
DelogX/defaults/plugins/delog_md_del/__init__.py
DelogX/defaults/plugins/delog_md_del/plugin.json
DelogX/defaults/plugins/delog_readmore/__init__.py
DelogX/defaults/plugins/delog_readmore/plugin.json
DelogX/defaults/plugins/delog_readmore/locale/en_US/locale.json
DelogX/defaults/plugins/delog_readmore/locale/zh_CN/locale.json
DelogX/defaults/plugins/delog_tags/__init__.py
DelogX/defaults/plugins/delog_tags/config.json
DelogX/defaults/plugins/delog_tags/plugin.json
DelogX/defaults/plugins/delog_tags/locale/en_US/locale.json
DelogX/defaults/plugins/delog_tags/locale/zh_CN/locale.json
DelogX/defaults/plugins/example_plugin/__init__.py
DelogX/defaults/plugins/example_plugin/plugin.json
DelogX/defaults/themes/default/404.html
DelogX/defaults/themes/default/footer.html
DelogX/defaults/themes/default/header.html
DelogX/defaults/themes/default/layout.html
DelogX/defaults/themes/default/list.html
DelogX/defaults/themes/default/page.html
DelogX/defaults/themes/default/post.html
DelogX/defaults/themes/default/static/style.css
DelogX/entity/__init__.py
DelogX/entity/bundle.py
DelogX/entity/error.py
DelogX/entity/item.py
DelogX/locale/en_US/demo.md
DelogX/locale/en_US/hello-delogx.md
DelogX/locale/en_US/locale.json
DelogX/locale/zh_CN/demo.md
DelogX/locale/zh_CN/hello-delogx.md
DelogX/locale/zh_CN/locale.json
DelogX/utils/__init__.py
DelogX/utils/compat.py
DelogX/utils/config.py
