Metadata-Version: 1.1
Name: DelogX
Version: 1.2.2
Summary: Yet another Markdown based blog
Home-page: http://delogx.deluxghost.me/
Author: deluxghost
Author-email: deluxghost@gmail.com
License: Apache License 2.0
Keywords: flask markdown blog framework
Platform: UNKNOWN
Classifier: Development Status :: 5 - Production/Stable
Classifier: Operating System :: OS Independent
Classifier: Intended Audience :: Developers
Classifier: Intended Audience :: System Administrators
Classifier: Framework :: Flask
Classifier: Programming Language :: Python :: 3
Classifier: Natural Language :: English
Classifier: Natural Language :: Chinese (Simplified)
Classifier: Topic :: Internet :: WWW/HTTP :: Dynamic Content
Classifier: Topic :: Internet :: WWW/HTTP :: WSGI :: Application
